daagy/__init__.py
daagy_ai-1.0.1.dist-info/licenses/LICENSE
daagy_ai-1.0.1.dist-info/METADATA
daagy_ai-1.0.1.dist-info/WHEEL
daagy_ai-1.0.1.dist-info/entry_points.txt
daagy_ai-1.0.1.dist-info/top_level.txt
daagy_ai-1.0.1.dist-info/RECORD
