Metadata-Version: 2.4
Name: daagy-ai
Version: 1.0.1
Summary: Daagy is a terminal-based AI assistant that follows natural language instructions to perform system tasks, answer questions, and much more.
Home-page: https://github.com/VibhorJaiswal/daagy-ai
Author: Vibhor Jaiswal
Author-email: vibhor.jaiswal9.9@gmail.com
Classifier: Programming Language :: Python :: 3
Classifier: License :: OSI Approved :: MIT License
Requires-Python: >=3.7
License-File: LICENSE
Requires-Dist: google-genai
Dynamic: author
Dynamic: author-email
Dynamic: classifier
Dynamic: description
Dynamic: description-content-type
Dynamic: home-page
Dynamic: license-file
Dynamic: requires-dist
Dynamic: requires-python
Dynamic: summary
